{
  "status": true,
  "data": {
    "id": "1201",
    "lokasi": "KAB. BANDUNG",
    "daerah": "JAWA BARAT",
    "koordinat": {
      "lat": -7.020611111111111,
      "lon": 107.52865833333334,
      "lintang": "7° 01' 14.2\" S",
      "bujur": "107° 31' 43.17\" E"
    },
    "jadwal": [
      {
        "tanggal": "Minggu, 01/08/2021",
        "imsak": "04:34",
        "subuh": "04:44",
        "terbit": "05:54",
        "dhuha": "06:27",
        "dzuhur": "12:00",
        "ashar": "15:21",
        "maghrib": "17:58",
        "isya": "19:06",
        "date": "2021-08-01"
      },
      {
        "tanggal": "Senin, 02/08/2021",
        "imsak": "04:33",
        "subuh": "04:43",
        "terbit": "05:54",
        "dhuha": "06:27",
        "dzuhur": "12:00",
        "ashar": "15:21",
        "maghrib": "17:58",
        "isya": "19:05",
        "date": "2021-08-02"
      },
      {
        "tanggal": "Selasa, 03/08/2021",
        "imsak": "04:33",
        "subuh": "04:43",
        "terbit": "05:54",
        "dhuha": "06:27",
        "dzuhur": "12:00",
        "ashar": "15:20",
        "maghrib": "17:58",
        "isya": "19:05",
        "date": "2021-08-03"
      },
      {
        "tanggal": "Rabu, 04/08/2021",
        "imsak": "04:33",
        "subuh": "04:43",
        "terbit": "05:54",
        "dhuha": "06:26",
        "dzuhur": "11:59",
        "ashar": "15:20",
        "maghrib": "17:58",
        "isya": "19:05",
        "date": "2021-08-04"
      },
      {
        "tanggal": "Kamis, 05/08/2021",
        "imsak": "04:33",
        "subuh": "04:43",
        "terbit": "05:54",
        "dhuha": "06:26",
        "dzuhur": "11:59",
        "ashar": "15:20",
        "maghrib": "17:58",
        "isya": "19:05",
        "date": "2021-08-05"
      },
      {
        "tanggal": "Jumat, 06/08/2021",
        "imsak": "04:33",
        "subuh": "04:43",
        "terbit": "05:53",
        "dhuha": "06:26",
        "dzuhur": "11:59",
        "ashar": "15:20",
        "maghrib": "17:58",
        "isya": "19:05",
        "date": "2021-08-06"
      },
      {
        "tanggal": "Sabtu, 07/08/2021",
        "imsak": "04:33",
        "subuh": "04:43",
        "terbit": "05:53",
        "dhuha": "06:25",
        "dzuhur": "11:59",
        "ashar": "15:20",
        "maghrib": "17:58",
        "isya": "19:05",
        "date": "2021-08-07"
      },
      {
        "tanggal": "Minggu, 08/08/2021",
        "imsak": "04:33",
        "subuh": "04:43",
        "terbit": "05:53",
        "dhuha": "06:25",
        "dzuhur": "11:59",
        "ashar": "15:20",
        "maghrib": "17:58",
        "isya": "19:05",
        "date": "2021-08-08"
      },
      {
        "tanggal": "Senin, 09/08/2021",
        "imsak": "04:33",
        "subuh": "04:43",
        "terbit": "05:53",
        "dhuha": "06:25",
        "dzuhur": "11:59",
        "ashar": "15:20",
        "maghrib": "17:58",
        "isya": "19:05",
        "date": "2021-08-09"
      },
      {
        "tanggal": "Selasa, 10/08/2021",
        "imsak": "04:32",
        "subuh": "04:42",
        "terbit": "05:52",
        "dhuha": "06:25",
        "dzuhur": "11:59",
        "ashar": "15:19",
        "maghrib": "17:58",
        "isya": "19:05",
        "date": "2021-08-10"
      },
      {
        "tanggal": "Rabu, 11/08/2021",
        "imsak": "04:32",
        "subuh": "04:42",
        "terbit": "05:52",
        "dhuha": "06:24",
        "dzuhur": "11:59",
        "ashar": "15:19",
        "maghrib": "17:58",
        "isya": "19:05",
        "date": "2021-08-11"
      },
      {
        "tanggal": "Kamis, 12/08/2021",
        "imsak": "04:32",
        "subuh": "04:42",
        "terbit": "05:52",
        "dhuha": "06:24",
        "dzuhur": "11:58",
        "ashar": "15:19",
        "maghrib": "17:58",
        "isya": "19:05",
        "date": "2021-08-12"
      },
      {
        "tanggal": "Jumat, 13/08/2021",
        "imsak": "04:32",
        "subuh": "04:42",
        "terbit": "05:51",
        "dhuha": "06:23",
        "dzuhur": "11:58",
        "ashar": "15:19",
        "maghrib": "17:58",
        "isya": "19:05",
        "date": "2021-08-13"
      },
      {
        "tanggal": "Sabtu, 14/08/2021",
        "imsak": "04:31",
        "subuh": "04:41",
        "terbit": "05:51",
        "dhuha": "06:23",
        "dzuhur": "11:58",
        "ashar": "15:18",
        "maghrib": "17:58",
        "isya": "19:04",
        "date": "2021-08-14"
      },
      {
        "tanggal": "Minggu, 15/08/2021",
        "imsak": "04:31",
        "subuh": "04:41",
        "terbit": "05:51",
        "dhuha": "06:23",
        "dzuhur": "11:58",
        "ashar": "15:18",
        "maghrib": "17:58",
        "isya": "19:04",
        "date": "2021-08-15"
      },
      {
        "tanggal": "Senin, 16/08/2021",
        "imsak": "04:31",
        "subuh": "04:41",
        "terbit": "05:50",
        "dhuha": "06:22",
        "dzuhur": "11:58",
        "ashar": "15:18",
        "maghrib": "17:58",
        "isya": "19:04",
        "date": "2021-08-16"
      },
      {
        "tanggal": "Selasa, 17/08/2021",
        "imsak": "04:31",
        "subuh": "04:41",
        "terbit": "05:50",
        "dhuha": "06:22",
        "dzuhur": "11:57",
        "ashar": "15:18",
        "maghrib": "17:58",
        "isya": "19:04",
        "date": "2021-08-17"
      },
      {
        "tanggal": "Rabu, 18/08/2021",
        "imsak": "04:30",
        "subuh": "04:40",
        "terbit": "05:50",
        "dhuha": "06:22",
        "dzuhur": "11:57",
        "ashar": "15:17",
        "maghrib": "17:58",
        "isya": "19:04",
        "date": "2021-08-18"
      },
      {
        "tanggal": "Kamis, 19/08/2021",
        "imsak": "04:30",
        "subuh": "04:40",
        "terbit": "05:49",
        "dhuha": "06:21",
        "dzuhur": "11:57",
        "ashar": "15:17",
        "maghrib": "17:58",
        "isya": "19:04",
        "date": "2021-08-19"
      },
      {
        "tanggal": "Jumat, 20/08/2021",
        "imsak": "04:30",
        "subuh": "04:40",
        "terbit": "05:49",
        "dhuha": "06:21",
        "dzuhur": "11:57",
        "ashar": "15:17",
        "maghrib": "17:58",
        "isya": "19:04",
        "date": "2021-08-20"
      },
      {
        "tanggal": "Sabtu, 21/08/2021",
        "imsak": "04:30",
        "subuh": "04:40",
        "terbit": "05:48",
        "dhuha": "06:20",
        "dzuhur": "11:57",
        "ashar": "15:16",
        "maghrib": "17:58",
        "isya": "19:03",
        "date": "2021-08-21"
      },
      {
        "tanggal": "Minggu, 22/08/2021",
        "imsak": "04:29",
        "subuh": "04:39",
        "terbit": "05:48",
        "dhuha": "06:20",
        "dzuhur": "11:56",
        "ashar": "15:16",
        "maghrib": "17:58",
        "isya": "19:03",
        "date": "2021-08-22"
      },
      {
        "tanggal": "Senin, 23/08/2021",
        "imsak": "04:29",
        "subuh": "04:39",
        "terbit": "05:48",
        "dhuha": "06:19",
        "dzuhur": "11:56",
        "ashar": "15:16",
        "maghrib": "17:58",
        "isya": "19:03",
        "date": "2021-08-23"
      },
      {
        "tanggal": "Selasa, 24/08/2021",
        "imsak": "04:29",
        "subuh": "04:39",
        "terbit": "05:47",
        "dhuha": "06:19",
        "dzuhur": "11:56",
        "ashar": "15:15",
        "maghrib": "17:57",
        "isya": "19:03",
        "date": "2021-08-24"
      },
      {
        "tanggal": "Rabu, 25/08/2021",
        "imsak": "04:28",
        "subuh": "04:38",
        "terbit": "05:47",
        "dhuha": "06:18",
        "dzuhur": "11:55",
        "ashar": "15:15",
        "maghrib": "17:57",
        "isya": "19:03",
        "date": "2021-08-25"
      },
      {
        "tanggal": "Kamis, 26/08/2021",
        "imsak": "04:28",
        "subuh": "04:38",
        "terbit": "05:46",
        "dhuha": "06:18",
        "dzuhur": "11:55",
        "ashar": "15:14",
        "maghrib": "17:57",
        "isya": "19:03",
        "date": "2021-08-26"
      },
      {
        "tanggal": "Jumat, 27/08/2021",
        "imsak": "04:27",
        "subuh": "04:37",
        "terbit": "05:46",
        "dhuha": "06:17",
        "dzuhur": "11:55",
        "ashar": "15:14",
        "maghrib": "17:57",
        "isya": "19:02",
        "date": "2021-08-27"
      },
      {
        "tanggal": "Sabtu, 28/08/2021",
        "imsak": "04:27",
        "subuh": "04:37",
        "terbit": "05:45",
        "dhuha": "06:17",
        "dzuhur": "11:55",
        "ashar": "15:13",
        "maghrib": "17:57",
        "isya": "19:02",
        "date": "2021-08-28"
      },
      {
        "tanggal": "Minggu, 29/08/2021",
        "imsak": "04:27",
        "subuh": "04:37",
        "terbit": "05:45",
        "dhuha": "06:16",
        "dzuhur": "11:54",
        "ashar": "15:13",
        "maghrib": "17:57",
        "isya": "19:02",
        "date": "2021-08-29"
      },
      {
        "tanggal": "Senin, 30/08/2021",
        "imsak": "04:26",
        "subuh": "04:36",
        "terbit": "05:44",
        "dhuha": "06:16",
        "dzuhur": "11:54",
        "ashar": "15:12",
        "maghrib": "17:57",
        "isya": "19:02",
        "date": "2021-08-30"
      },
      {
        "tanggal": "Selasa, 31/08/2021",
        "imsak": "04:26",
        "subuh": "04:36",
        "terbit": "05:44",
        "dhuha": "06:15",
        "dzuhur": "11:54",
        "ashar": "15:12",
        "maghrib": "17:57",
        "isya": "19:02",
        "date": "2021-08-31"
      }
    ]
  }
}
